[
    {
        "id": 2788062,
        "uuid": "de0542909fd34693b4d43c317671f180",
        "nickname": "ChasHilll",
        "email": "kampungb.a.r.upro.duc.t@gmail.com",
        "webid": "1748518071821dvk9sj36",
        "token": "e38d7a22c63b493cbd1c5401f06b7b122788062de054"
    },
    {
        "id": 2788063,
        "uuid": "8fda687cc9164957ad351d22fd69cbee",
        "nickname": "West_VerenashireBrownPrime",
        "email": "kampungb.a.r.upro.du.ct@gmail.com",
        "webid": "1748518074184htohibaj",
        "token": "6e7228f753404872b04616bdf9f49c7827880638fda6"
    },
    {
        "id": 2788064,
        "uuid": "4301923f3f9e44bcb49144fe429ed712",
        "nickname": "RodolfoKulas",
        "email": "kampungb.a.r.upro.du.c.t@gmail.com",
        "webid": "1748518076643bom6b1dn",
        "token": "8d7779cfacbb47ac8a081036fd48d462278806443019"
    },
    {
        "id": 2788065,
        "uuid": "88b4f280c89a48b69260334cea9f59ed",
        "nickname": "kasey_nikolaus",
        "email": "kampungb.a.r.upro.d.uct@gmail.com",
        "webid": "1748518079022xwdibhql",
        "token": "531d8454c5da4b608017d87e0670670a278806588b4f"
    },
    {
        "id": 2788066,
        "uuid": "20465dced1274852a878d50a02676091",
        "nickname": "ChungWyman",
        "email": "kampungb.a.r.upro.d.uc.t@gmail.com",
        "webid": "1748518081588wtgwzaey",
        "token": "7cc4760a2333419887cc04cd4c309d57278806620465"
    },
    {
        "id": 2788067,
        "uuid": "396c03466f524bdfbe9fa29e8b85263c",
        "nickname": "jan_carroll",
        "email": "kampungb.a.r.upro.d.u.ct@gmail.com",
        "webid": "17485180841743jtdzdha",
        "token": "251066197f1a4af6a39045cc5a96e2172788067396c0"
    },
    {
        "id": 2788068,
        "uuid": "858f795c165d4e98b6d1189b390fecfe",
        "nickname": "GregoryBrekke",
        "email": "kampungb.a.r.upro.d.u.c.t@gmail.com",
        "webid": "1748518086679sdrxdb5c",
        "token": "4949c118d3af435895b0ab322bc7e3eb2788068858f7"
    },
    {
        "id": 2788069,
        "uuid": "861e9da69f434da4960daa40468e9152",
        "nickname": "jen_wuckert",
        "email": "kampungb.a.r.upr.oduct@gmail.com",
        "webid": "1748518088974a97pdurp",
        "token": "7f4b871694ff452aae90fbedbece763c2788069861e9"
    },
    {
        "id": 2788070,
        "uuid": "e549ab9f502c4dd3a1e667b92440fc9b",
        "nickname": "ZonaParker",
        "email": "kampungb.a.r.upr.oduc.t@gmail.com",
        "webid": "1748518091583qfef2t3p",
        "token": "db2de2e7d25649cf890b201bf31416022788070e549a"
    },
    {
        "id": 2788071,
        "uuid": "b935da6d1d6949fc97f67633e5360553",
        "nickname": "lupe_ankunding",
        "email": "kampungb.a.r.upr.odu.ct@gmail.com",
        "webid": "1748518094338tlwupnss",
        "token": "cbdc8c3ca74a450b9d8148a725c48b752788071b935d"
    },
    {
        "id": 2788072,
        "uuid": "f1ae5851fbdd4adb981640fca350594a",
        "nickname": "PamalaVolkman",
        "email": "kampungb.a.r.upr.odu.c.t@gmail.com",
        "webid": "1748518097143lxl98csw",
        "token": "0f85136513ff4cc6b5c4a84b10555a142788072f1ae5"
    },
    {
        "id": 2788073,
        "uuid": "12fe560ce3c1401e86804d3926246956",
        "nickname": "blair_kshlerin",
        "email": "kampungb.a.r.upr.od.uct@gmail.com",
        "webid": "1748518099736ie7rgxk2",
        "token": "96d8c07875a040ccb7c9df7f6ec8a586278807312fe5"
    },
    {
        "id": 2788074,
        "uuid": "f6d508421f8e4663a48fd131d8073851",
        "nickname": "TaylorThompson",
        "email": "kampungb.a.r.upr.od.uc.t@gmail.com",
        "webid": "1748518102442c3sgtbub",
        "token": "ff9481fde0934d2db05b2ba9086df6922788074f6d50"
    },
    {
        "id": 2788075,
        "uuid": "1a1fafc155e0487182e5683ae9ca4820",
        "nickname": "lizabeth_mitchell",
        "email": "kampungb.a.r.upr.od.u.ct@gmail.com",
        "webid": "1748518104807dby4g6yn",
        "token": "db59d329ac4b425092ed9746f0862a3027880751a1fa"
    },
    {
        "id": 2788076,
        "uuid": "5f15a793183a4ae395056249f209dc2a",
        "nickname": "WallyWiegand",
        "email": "kampungb.a.r.upr.od.u.c.t@gmail.com",
        "webid": "1748518107978fp7lwcxl",
        "token": "60c28e4661fc4cb280b726b5112c6da127880765f15a"
    },
    {
        "id": 2788077,
        "uuid": "7edec29ae5784c14859fa058fc7d618c",
        "nickname": "North_ChadportSauerPrime",
        "email": "kampungb.a.r.upr.o.duct@gmail.com",
        "webid": "1748518111041tb4dxlvl",
        "token": "002f26ecdec3401db769cc31fb20185d27880777edec"
    },
    {
        "id": 2788079,
        "uuid": "d9d00d4ff6da46508f2dfae3864b525a",
        "nickname": "ramon_rowe",
        "email": "kampungb.a.r.upr.o.duc.t@gmail.com",
        "webid": "1748518113493px0qfddv",
        "token": "a91ddd5eeec341108c1a18cbe9581f3b2788079d9d00"
    },
    {
        "id": 2788080,
        "uuid": "5dd19cf88591461db0489b3bcd22f1e7",
        "nickname": "DennaLubowitz",
        "email": "kampungb.a.r.upr.o.du.ct@gmail.com",
        "webid": "17485181159776ppzqktq",
        "token": "6584fd078d734c6e97b0bc8001d77b1927880805dd19"
    },
    {
        "id": 2788081,
        "uuid": "5f2b686d4eda46ce802626f9eda3e45f",
        "nickname": "kirby_lemke",
        "email": "kampungb.a.r.upr.o.du.c.t@gmail.com",
        "webid": "1748518118566lta66luj",
        "token": "5f1a48cf05f149368a46bc6f4d9a450e27880815f2b6"
    },
    {
        "id": 2788082,
        "uuid": "9b7b455809054f008ec0aca863f5a220",
        "nickname": "AngelicaPurdy",
        "email": "kampungb.a.r.upr.o.d.uct@gmail.com",
        "webid": "1748518121544huj3bt0x",
        "token": "fce5284827864ea79ac30742fd1b13c327880829b7b4"
    },
    {
        "id": 2788083,
        "uuid": "60d6785f5fe248728c797ee9b91e3716",
        "nickname": "herschel_price",
        "email": "kampungb.a.r.upr.o.d.uc.t@gmail.com",
        "webid": "17485181238146cc6h0zi",
        "token": "cd54898050f045ecbddc17fef154ecdc278808360d67"
    },
    {
        "id": 2788084,
        "uuid": "d4e4849e99134b7e9fc9a0b4bf990f95",
        "nickname": "JuniorLueilwitz",
        "email": "kampungb.a.r.upr.o.d.u.ct@gmail.com",
        "webid": "1748518126255rlq2h1wk",
        "token": "a3849fbe66544facb79d9626d5fc9fc52788084d4e48"
    },
    {
        "id": 2788085,
        "uuid": "ed3754001d4346d0b70058967d061e24",
        "nickname": "janina_funk",
        "email": "kampungb.a.r.upr.o.d.u.c.t@gmail.com",
        "webid": "1748518128960sxbcz8sr",
        "token": "701d654697a94aaf8f8e87bf33551ab82788085ed375"
    },
    {
        "id": 2788086,
        "uuid": "a95f447121c84fe4b73bc10fa7d0cd6a",
        "nickname": "LoydMrazAI",
        "email": "kampungb.a.r.up.roduct@gmail.com",
        "webid": "1748518131366mor0yfb3",
        "token": "fa1217bd6cad46dba35aa97cd6e352512788086a95f4"
    },
    {
        "id": 2788087,
        "uuid": "1acd5e2b6bdc4dfabb78d14c41a14b70",
        "nickname": "Natacha_wittingAI",
        "email": "kampungb.a.r.up.roduc.t@gmail.com",
        "webid": "17485181340430ghuokzm",
        "token": "93914488e1b4432b9507ce1c1f1b51d827880871acd5"
    },
    {
        "id": 2788088,
        "uuid": "a03c560517d640818d3add0492343df6",
        "nickname": "WhitneyMurazikAI",
        "email": "kampungb.a.r.up.rodu.ct@gmail.com",
        "webid": "1748518136875nu3ri3tz",
        "token": "766008d612834db788f42c90b80c1aaa2788088a03c5"
    },
    {
        "id": 2788089,
        "uuid": "11b7e127e46a4105a6938a2f796f5c54",
        "nickname": "Dahlia_volkmanAI",
        "email": "kampungb.a.r.up.rodu.c.t@gmail.com",
        "webid": "1748518139113m6ocmuw4",
        "token": "7e2253e4e2f043ce8e60717d9d0fde1e278808911b7e"
    },
    {
        "id": 2788090,
        "uuid": "3d9a479f9c8b4744ba9de5d5e4685dd9",
        "nickname": "JohanaReillyAI",
        "email": "kampungb.a.r.up.rod.uct@gmail.com",
        "webid": "1748518141753xvmjmhfe",
        "token": "edb73ed97b344b209c6c26d8e283d7f127880903d9a4"
    },
    {
        "id": 2788091,
        "uuid": "90ed10acc637467c83fccbbc88c15e0d",
        "nickname": "kampungb.a.r.up.rod.uc.t",
        "email": "kampungb.a.r.up.rod.uc.t@gmail.com",
        "webid": "1748518144221ph8krjns",
        "token": "1e8d2a74b82e483b838b8d0c5cf8ef11278809190ed1"
    },
    {
        "id": 2788092,
        "uuid": "5e4029b07ef84d2e8b7a58c6a692da5e",
        "nickname": "LoycePriceArt",
        "email": "kampungb.a.r.up.rod.u.ct@gmail.com",
        "webid": "1748518146434vjqomjzm",
        "token": "4ee7dd6b390f47699d3ec5d279ce4a3727880925e402"
    },
    {
        "id": 2788093,
        "uuid": "5630acbdf7094b56b6f3967a182678f4",
        "nickname": "Maple_runolfsdottirArt",
        "email": "kampungb.a.r.up.rod.u.c.t@gmail.com",
        "webid": "1748518148850uhk0gfx5",
        "token": "88f2b862f0a24419a2ffe029f52331a327880935630a"
    },
    {
        "id": 2788094,
        "uuid": "1dc34f8b37064656b8de204d8ea6e8ac",
        "nickname": "KatherynPowlowskiArt",
        "email": "kampungb.a.r.up.ro.duct@gmail.com",
        "webid": "1748518151609gshsdhaw",
        "token": "bc87e923f9cb462dbcd15fdade8a944527880941dc34"
    },
    {
        "id": 2788095,
        "uuid": "76c6d4e228344a6ab461a5d9e46a42f6",
        "nickname": "Sylvester_friesenArt",
        "email": "kampungb.a.r.up.ro.duc.t@gmail.com",
        "webid": "1748518154068glbua3mz",
        "token": "056065584353499ba7e7de7de51295fe278809576c6d"
    },
    {
        "id": 2788096,
        "uuid": "7c534e7a8bdc479b937e2ad98267ea91",
        "nickname": "MonroeLangDesign",
        "email": "kampungb.a.r.up.ro.du.ct@gmail.com",
        "webid": "17485181571202cjzwtzl",
        "token": "4225f1353e434e88941ced53d992979927880967c534"
    },
    {
        "id": 2788097,
        "uuid": "6d6c4469231243c5810558f1c801fe84",
        "nickname": "Hassan_howellDesign",
        "email": "kampungb.a.r.up.ro.du.c.t@gmail.com",
        "webid": "174851815969107bmdxe3",
        "token": "979254957e4943d9ba8a413f499e404b27880976d6c4"
    },
    {
        "id": 2788098,
        "uuid": "06ed79f6a32c4e18ada9ad2211fcf216",
        "nickname": "RickyFerryDesign",
        "email": "kampungb.a.r.up.ro.d.uct@gmail.com",
        "webid": "1748518162482nqamtpud",
        "token": "832fab1742d441a19abff57adf752ecc278809806ed7"
    },
    {
        "id": 2788099,
        "uuid": "9d85169ea01446b1b109d13c686445fa",
        "nickname": "Xavier_reichertDesign",
        "email": "kampungb.a.r.up.ro.d.uc.t@gmail.com",
        "webid": "1748518165760eb7dqyry",
        "token": "dae88bea30bb41489f3b5546e5d8040427880999d851"
    },
    {
        "id": 2788100,
        "uuid": "9f170fb7575444459be3a5b4d37a0a13",
        "nickname": "JenniKozey",
        "email": "kampungb.a.r.up.ro.d.u.ct@gmail.com",
        "webid": "1748518168480utqo3n9r",
        "token": "580861824421432191a987fbd9fd4c2427881009f170"
    },
    {
        "id": 2788101,
        "uuid": "14a398944393475084b42ce09aa46766",
        "nickname": "adrianne_pfannerstill",
        "email": "kampungb.a.r.up.ro.d.u.c.t@gmail.com",
        "webid": "1748518171293jq2i98si",
        "token": "b71ed1f8a8ba4069a9d9e35807330183278810114a39"
    },
    {
        "id": 2788102,
        "uuid": "bb1aa197a24e4ab5ac9d03a829314390",
        "nickname": "GeorgettaRoob",
        "email": "kampungb.a.r.up.r.oduct@gmail.com",
        "webid": "1748518174352dq0ywlih",
        "token": "5fcc2dfc203f4d908ac673bbdd1871472788102bb1aa"
    },
    {
        "id": 2788103,
        "uuid": "ee8f9f7d73574246b37e67ce6ee436c9",
        "nickname": "anderson_rolfson",
        "email": "kampungb.a.r.up.r.oduc.t@gmail.com",
        "webid": "1748518176913po0d1i40",
        "token": "2dbf7ecec371437883d74b12d58c31582788103ee8f9"
    },
    {
        "id": 2788193,
        "uuid": "bbc01c05d0654f5caa2b7608460dc246",
        "nickname": "Ernest_mcclureArt",
        "email": "kampungb.a.r.up.r.odu.c.t@gmail.com",
        "webid": "1748518182340gbneuyte",
        "token": "73554d5291d44327b4ed959378c2047e2788193bbc01"
    },
    {
        "id": 2788194,
        "uuid": "2588b57f49834f748f5efc9f28fceb01",
        "nickname": "LukeGutmannArt",
        "email": "kampungb.a.r.up.r.od.uct@gmail.com",
        "webid": "1748518184814m6dtkvlc",
        "token": "4b8b58adc7f84bf0b6dc329117736bab27881942588b"
    },
    {
        "id": 2788686,
        "uuid": "b6c254e967fc4635b1511c89871fec7b",
        "nickname": "ShanellSpinkaAI",
        "email": "kampung.barupr.o.du.ct@gmail.com",
        "webid": "1748518187502ud0u5pz6",
        "token": "78f3bfda49464cfc89d01d036b3d96cc2788686b6c25"
    },
    {
        "id": 2788687,
        "uuid": "4981125d85d9416d9c43737b8794f375",
        "nickname": "Jay_ferryAI",
        "email": "kampung.barupr.o.du.c.t@gmail.com",
        "webid": "1748518189918hbmxlwqn",
        "token": "0e9cd998dfe444a99cf958e5e9058093278868749811"
    },
    {
        "id": 2788688,
        "uuid": "af2d5fb39ad4453bb13c5adcd84c6382",
        "nickname": "ClaytonOrtizAI",
        "email": "kampung.barupr.o.d.uct@gmail.com",
        "webid": "1748518192784w4ylf4j1",
        "token": "3d9d959681684d3e89aba6b81b1015df2788688af2d5"
    },
    {
        "id": 2788689,
        "uuid": "1970cb5ea821415bad5230ca7cac54ee",
        "nickname": "Wilhelmina_wintheiserAI",
        "email": "kampung.barupr.o.d.uc.t@gmail.com",
        "webid": "1748518195841481i9x5x",
        "token": "e8387e1b7c2b4f81b3ea1d4f779caced27886891970c"
    },
    {
        "id": 2788690,
        "uuid": "b1e2768c4a67458e80920777738dbe3c",
        "nickname": "EvelinStammAI",
        "email": "kampung.barupr.o.d.u.ct@gmail.com",
        "webid": "1748518198178bnhlyu1m",
        "token": "63049760a19b43999228a3a5c71b170f2788690b1e27"
    },
    {
        "id": 2788691,
        "uuid": "84b9efccc504429ebfbb4df3338015ef",
        "nickname": "North_AntonettaConroyPrimeArt",
        "email": "kampung.barupr.o.d.u.c.t@gmail.com",
        "webid": "1748518200434g9ud39pr",
        "token": "65496c83f4094010a218c2d6a1f042ab278869184b9e"
    },
    {
        "id": 2788692,
        "uuid": "47884b131fad420d9f31ed4d1024da9d",
        "nickname": "AdaWalshArt",
        "email": "kampung.barup.roduct@gmail.com",
        "webid": "1748518780394unrg6qox",
        "token": "16be94baa25d4598bd6a03547dded6ab278869247884"
    },
    {
        "id": 2788693,
        "uuid": "cdd2ca49a2304bc6a2d704c290347e54",
        "nickname": "Jonna_kirlinArt",
        "email": "kampung.barup.roduc.t@gmail.com",
        "webid": "1748518782990r89nlrnn",
        "token": "644f1fd3fff54d0da7f4691902822f062788693cdd2c"
    },
    {
        "id": 2788694,
        "uuid": "5476de045ebd4cae8909d93c3e88ee95",
        "nickname": "EvonYostArt",
        "email": "kampung.barup.rodu.ct@gmail.com",
        "webid": "1748518785368s4w5dimg",
        "token": "b009eda0b57941788318abbdaefac1b727886945476d"
    },
    {
        "id": 2788695,
        "uuid": "744921edd74f4b1695e243ccd4528b3b",
        "nickname": "Waldo_handArt",
        "email": "kampung.barup.rodu.c.t@gmail.com",
        "webid": "1748518787812smyybyig",
        "token": "91431f17091f457d8ec704925304597b278869574492"
    },
    {
        "id": 2788696,
        "uuid": "6b6c79d946964dcd85a87a348d9c0c87",
        "nickname": "MarloWymanDesign",
        "email": "kampung.barup.rod.uct@gmail.com",
        "webid": "1748518790337xpauvzqz",
        "token": "98b6945874374b0394f38f71a1051f2d27886966b6c7"
    },
    {
        "id": 2788697,
        "uuid": "e06a0920e4ab4eb9981198ac933c2f08",
        "nickname": "Brittaney_harrisDesign",
        "email": "kampung.barup.rod.uc.t@gmail.com",
        "webid": "1748518792791ouhdcbt3",
        "token": "9ae68d48246f47cfa44cd70081fc055c2788697e06a0"
    },
    {
        "id": 2788698,
        "uuid": "1bf34168cef0445da2cb136994ee01ec",
        "nickname": "JarrettBernhardDesign",
        "email": "kampung.barup.rod.u.ct@gmail.com",
        "webid": "17485187954061js0w3kc",
        "token": "b3d051d273bc40f8a152c03207bebf8927886981bf34"
    },
    {
        "id": 2788699,
        "uuid": "7763e74aa7474b35a676129526725043",
        "nickname": "Phillip_stehrDesign",
        "email": "kampung.barup.rod.u.c.t@gmail.com",
        "webid": "1748518797935vtfblsz1",
        "token": "bc53f181587b48de90de64a27e0a1b0927886997763e"
    },
    {
        "id": 2788701,
        "uuid": "acf128e79ae84644aaf3c4c90b140832",
        "nickname": "kampung.barup.ro.duct",
        "email": "kampung.barup.ro.duct@gmail.com",
        "webid": "1748518800015t41bqo9o",
        "token": "5b9429dfaba142d4bb7e4468cdae2ef12788701acf12"
    },
    {
        "id": 2788702,
        "uuid": "571ebef04d2848d78c24a207dfeacda4",
        "nickname": "LissaStamm",
        "email": "kampung.barup.ro.duc.t@gmail.com",
        "webid": "1748518802604m9iaxvr3",
        "token": "7c501c011a574586b60f70afd72548962788702571eb"
    },
    {
        "id": 2788704,
        "uuid": "74aac31742e54b71871175dfa8c38e11",
        "nickname": "LesterGrady",
        "email": "kampung.barup.ro.du.ct@gmail.com",
        "webid": "1748518805065zvnypoes",
        "token": "6003ead13d0a44dc85ef3a71022a2739278870474aac"
    },
    {
        "id": 2788705,
        "uuid": "9b847365793a4f96b7e357ff26f42bd1",
        "nickname": "stephania_wintheiser",
        "email": "kampung.barup.ro.du.c.t@gmail.com",
        "webid": "1748518807329ezrhevlq",
        "token": "615d347ea28c4912b0eab1d3db4d494627887059b847"
    },
    {
        "id": 2788706,
        "uuid": "9a0ae730a7c749a5ab3b0a39efd099db",
        "nickname": "CathrynWalsh",
        "email": "kampung.barup.ro.d.uct@gmail.com",
        "webid": "1748518809633mvbcb03l",
        "token": "bedc95616aa94b9fa4121d8dcedea73927887069a0ae"
    },
    {
        "id": 2788707,
        "uuid": "ff41a814965d495e8cda4d78ba1ff8bd",
        "nickname": "West_LakeshiaKuvalisPrime",
        "email": "kampung.barup.ro.d.uc.t@gmail.com",
        "webid": "1748518812113uvwufpwn",
        "token": "040dc8f18d4a41c0ab5ce327070c89222788707ff41a"
    },
    {
        "id": 2788709,
        "uuid": "20e05a1ffe89450f81f243cb589ac3af",
        "nickname": "carey_mante",
        "email": "kampung.barup.ro.d.u.ct@gmail.com",
        "webid": "1748518814746cbmc1mhy",
        "token": "c0bd12dca94d484a914f164cd5695381278870920e05"
    },
    {
        "id": 2788710,
        "uuid": "db3c0b4af3df457f8dd8454e9ba096cd",
        "nickname": "ValentineDickinson",
        "email": "kampung.barup.ro.d.u.c.t@gmail.com",
        "webid": "17485188172546udmoh6i",
        "token": "66d6ff5c24cb4768a3123cb32f80abc32788710db3c0"
    },
    {
        "id": 2788711,
        "uuid": "8316d9649f6d495387b41d3164545ec8",
        "nickname": "chanda_wiza",
        "email": "kampung.barup.r.oduct@gmail.com",
        "webid": "17485188198502kndt7k0",
        "token": "a06db4006c9f468aaed6ac943b76a15a27887118316d"
    },
    {
        "id": 2788712,
        "uuid": "ba9dac24bca0469a85ad79a908f8da1e",
        "nickname": "GeorgeannaBarton",
        "email": "kampung.barup.r.oduc.t@gmail.com",
        "webid": "17485188223097bkg0xcs",
        "token": "81cffd47716749a48f6ca215b63c4e832788712ba9da"
    },
    {
        "id": 2788714,
        "uuid": "0e0b229b3bc54ddeb140dbf8cbc8d80e",
        "nickname": "kampung.barup.r.odu.ct",
        "email": "kampung.barup.r.odu.ct@gmail.com",
        "webid": "1748518824650fcrwou7r",
        "token": "381b1756020e457bb020e73a7c12ea6b27887140e0b2"
    },
    {
        "id": 2788715,
        "uuid": "83280173b7d54fe59ccf49230905f754",
        "nickname": "dana_predovic",
        "email": "kampung.barup.r.odu.c.t@gmail.com",
        "webid": "1748518827535tryear3j",
        "token": "ab7972aab9e342cb832f62d0589404ac278871583280"
    },
    {
        "id": 2788716,
        "uuid": "ca96dcdede7f4466bcf8057c7d8eb462",
        "nickname": "MandiOKeefe",
        "email": "kampung.barup.r.od.uct@gmail.com",
        "webid": "1748518829852bnnzqqef",
        "token": "647b71fbde334f1ea0d2ca2efa4b7c5a2788716ca96d"
    },
    {
        "id": 2788718,
        "uuid": "546b056ce49e4b72b7c37214eb7400c0",
        "nickname": "StaceyMcCullough",
        "email": "kampung.barup.r.od.uc.t@gmail.com",
        "webid": "1748518832169iohfgp5y",
        "token": "8357660b9e2d4b768c95fe30f0d928282788718546b0"
    },
    {
        "id": 2788719,
        "uuid": "a4d64eeeab794a30b13fcb42f036bf3f",
        "nickname": "kampung.barup.r.od.u.ct",
        "email": "kampung.barup.r.od.u.ct@gmail.com",
        "webid": "1748518834701evcmp62f",
        "token": "e1d1c2b85aad4095ad414189cff114752788719a4d64"
    },
    {
        "id": 2788720,
        "uuid": "2eadeb8d6a8b4824aa6471215cd06ba8",
        "nickname": "kampung.barup.r.od.u.c.t",
        "email": "kampung.barup.r.od.u.c.t@gmail.com",
        "webid": "1748518837194dge58vig",
        "token": "77ac9df4bb0c4234980d2d60dc1a7bf127887202eade"
    },
    {
        "id": 2788721,
        "uuid": "038b16f661d840249c840bd491931cfd",
        "nickname": "kampung.barup.r.o.duct",
        "email": "kampung.barup.r.o.duct@gmail.com",
        "webid": "1748518839657tuedtwa0",
        "token": "7e759e47a9114c5db422004d5cf85ecd2788721038b1"
    },
    {
        "id": 2788722,
        "uuid": "d8adf9778c51404ea51d20edaef1afcb",
        "nickname": "PedroCrist",
        "email": "kampung.barup.r.o.duc.t@gmail.com",
        "webid": "1748518842028tuyr5ycw",
        "token": "dc9c0d1d2bf94fa0ba84e3b5756dd2932788722d8adf"
    },
    {
        "id": 2788723,
        "uuid": "649e43f401f24761985116a153c54048",
        "nickname": "angelita_witting",
        "email": "kampung.barup.r.o.du.ct@gmail.com",
        "webid": "1748518844283dbgamy0s",
        "token": "7db5647fbdbc45b0a0a9ea14fa885abb2788723649e4"
    },
    {
        "id": 2788724,
        "uuid": "dbb03fd7b6c14d4e8be6b608b57a1f62",
        "nickname": "kampung.barup.r.o.du.c.t",
        "email": "kampung.barup.r.o.du.c.t@gmail.com",
        "webid": "1748518846957evzjr82s",
        "token": "9511722c3ffb4c0bad210a89b6d1f0932788724dbb03"
    },
    {
        "id": 2788725,
        "uuid": "ef059f939dd44bbb86a18c9b22c5b3ad",
        "nickname": "arlen_grady",
        "email": "kampung.barup.r.o.d.uct@gmail.com",
        "webid": "1748518849208kjsmkcze",
        "token": "ef330f55a5014b9d8a849dbfa3112d532788725ef059"
    },
    {
        "id": 2788726,
        "uuid": "ac1f03c0a6fc4ec5acd28f5502af3cb9",
        "nickname": "RonaldBartoletti",
        "email": "kampung.barup.r.o.d.uc.t@gmail.com",
        "webid": "1748518851812scwf07ey",
        "token": "c79bc3d905eb4dac888dfe1d6efef0552788726ac1f0"
    },
    {
        "id": 2788728,
        "uuid": "902b6e301d4242f4a58ffe0c0162f5df",
        "nickname": "DalilaBraun",
        "email": "kampung.barup.r.o.d.u.ct@gmail.com",
        "webid": "1748518854443j7wp4ils",
        "token": "4440eb5b417c40e39798abbb9aa433ae2788728902b6"
    },
    {
        "id": 2788729,
        "uuid": "8f3576efe8a94f1693c6f6765eb2aec6",
        "nickname": "kisha_jacobi",
        "email": "kampung.barup.r.o.d.u.c.t@gmail.com",
        "webid": "174851885676592ym0r2z",
        "token": "3cc2b0372f4f447d891fd21832a9838b27887298f357"
    },
    {
        "id": 2788730,
        "uuid": "70a372fbe5d742869877f7bbbe318737",
        "nickname": "WillHamill",
        "email": "kampung.baru.product@gmail.com",
        "webid": "1748518859068zi87epoc",
        "token": "09165cfeecca4bf7b019c9561d392f85278873070a37"
    },
    {
        "id": 2788731,
        "uuid": "85c4bb9cb1fb46d6b76fa26a9a8a7605",
        "nickname": "vivan_nader",
        "email": "kampung.baru.produc.t@gmail.com",
        "webid": "17485188616428hyjptxf",
        "token": "c7551739aa3041afa40ec3fb8bcc25b4278873185c4b"
    },
    {
        "id": 2788732,
        "uuid": "d44e5cecf5904f20a159632997466470",
        "nickname": "OdisReichert",
        "email": "kampung.baru.produ.ct@gmail.com",
        "webid": "17485188642174c9f3d9d",
        "token": "c4e8155272d44e8cacc5e12d47850e572788732d44e5"
    },
    {
        "id": 2788733,
        "uuid": "f6e319e99b9a46a3bc4fc8828064ecf9",
        "nickname": "christoper_friesen",
        "email": "kampung.baru.produ.c.t@gmail.com",
        "webid": "1748518867043sln31hhq",
        "token": "0c37ac502d8b470bb6311c3807b60c902788733f6e31"
    },
    {
        "id": 2788735,
        "uuid": "1375b7f79710487fba5c8b5d6d659c67",
        "nickname": "Lake_BridgettfortChristiansenPrime",
        "email": "kampung.baru.prod.uct@gmail.com",
        "webid": "1748518869085vtua1z6u",
        "token": "f19475a6ad104353850e0b88a905946b27887351375b"
    },
    {
        "id": 2788736,
        "uuid": "0391c6639a944b6690e68ed002f005cd",
        "nickname": "ZackaryGutkowski",
        "email": "kampung.baru.prod.uc.t@gmail.com",
        "webid": "1748518871508v9abrzkd",
        "token": "9f5beeb67b764cb996572c3ff8b71fc527887360391c"
    },
    {
        "id": 2788737,
        "uuid": "55c96530f35f42799abfaaaca06160e8",
        "nickname": "vernell_armstrong",
        "email": "kampung.baru.prod.u.ct@gmail.com",
        "webid": "1748518873847w5ppst7a",
        "token": "fb6ffe85af9f4deea73f5647b5442895278873755c96"
    },
    {
        "id": 2788738,
        "uuid": "9509881e6b20477b831695ae40e71123",
        "nickname": "ArleanFisher",
        "email": "kampung.baru.prod.u.c.t@gmail.com",
        "webid": "1748518876138anv27rwj",
        "token": "a8b02e7d8146472aa2e7cd9e59040a76278873895098"
    },
    {
        "id": 2788740,
        "uuid": "e61bea52e7d84a18a73fc71f0dbe15be",
        "nickname": "ElizebethHayes",
        "email": "kampung.baru.pro.duct@gmail.com",
        "webid": "1748518881323xyfoxvad",
        "token": "1e6889c0eedc4ac2a7d9705af3d27f1a2788740e61be"
    },
    {
        "id": 2788741,
        "uuid": "438dff29bc814e35aa7e3d88269a0edc",
        "nickname": "deanne_jones",
        "email": "kampung.baru.pro.duc.t@gmail.com",
        "webid": "1748518883704bobm3kku",
        "token": "ea1fadc4b40744a9bb095153e46d84172788741438df"
    },
    {
        "id": 2788742,
        "uuid": "26b68d476de940b48e5f6343ed8257a0",
        "nickname": "QuintonFeil",
        "email": "kampung.baru.pro.du.ct@gmail.com",
        "webid": "1748518886013naruwmav",
        "token": "6c7b4623656648f297b217acd5e52cd3278874226b68"
    },
    {
        "id": 2788743,
        "uuid": "012ded1809254a2ca81194c94f2d8a45",
        "nickname": "vincenzo_mueller",
        "email": "kampung.baru.pro.du.c.t@gmail.com",
        "webid": "1748518888557pr6a7jyz",
        "token": "392f30cfe3a8470eab09ca345e64d4072788743012de"
    },
    {
        "id": 2788789,
        "uuid": "7bc11d5f91394f16b13860b7702b69e2",
        "nickname": "Jorge_kleinAI",
        "email": "kampung.baru.pro.d.uct@gmail.com",
        "webid": "1748518891058tjcqiu9g",
        "token": "b64f8cb2e8224d43959cb754a30f3a8427887897bc11"
    },
    {
        "id": 2788790,
        "uuid": "9f9ea23e9be041198eba76d37b36c731",
        "nickname": "LewisSmithAI",
        "email": "kampung.baru.pro.d.uc.t@gmail.com",
        "webid": "1748518893330ejnsz9kw",
        "token": "109847bdde7044748335b18de3179fc627887909f9ea"
    },
    {
        "id": 2788791,
        "uuid": "3fef69034e064afb8013cd29c079a22c",
        "nickname": "East_TristaJohnsonPrimeArt",
        "email": "kampung.baru.pro.d.u.ct@gmail.com",
        "webid": "1748518895979hrgvku9u",
        "token": "fdf563a90a954556932e05f7621245d827887913fef6"
    },
    {
        "id": 2788793,
        "uuid": "0d8240f3011c43289136c63fd2c32764",
        "nickname": "Forrest_friesenArt",
        "email": "kampung.baru.pro.d.u.c.t@gmail.com",
        "webid": "1748518898308hyjphh9q",
        "token": "e3cb746d42ed4318a1e085864b6b90b427887930d824"
    },
    {
        "id": 2788794,
        "uuid": "758700d7d53d4af88264bd7bb19a53a0",
        "nickname": "NatalieReillyArt",
        "email": "kampung.baru.pr.oduct@gmail.com",
        "webid": "1748518901035gi1euwij",
        "token": "50408b4d63cb47b8b08fec9396b9d915278879475870"
    },
    {
        "id": 2788795,
        "uuid": "a282bd6a66af43b3b003534ac557ec2f",
        "nickname": "Hattie_rutherfordArt",
        "email": "kampung.baru.pr.oduc.t@gmail.com",
        "webid": "1748518903276hrx2emmv",
        "token": "78ebc14feae24506ac36097e3b6446222788795a282b"
    },
    {
        "id": 2958032,
        "uuid": "5a59643157884c1e9ae9bcb0a6bd0164",
        "nickname": "kampungb.a.r.up.r.odu.ct",
        "email": "kampungb.a.r.up.r.odu.ct@gmail.com",
        "webid": "1748518179875xuyfh57t",
        "token": "98e9c0f68f0046a497e588aad3ec1ac629580325a596"
    }
]
